lamoom_cicd/__init__.py
lamoom_cicd/exceptions.py
lamoom_cicd/prompts/prompt_compare_results.py
lamoom_cicd/prompts/prompt_generate_facts.py
lamoom_cicd/responses.py
lamoom_cicd/test_llm_response.py
lamoom_cicd/utils.py
lamoom_cicd-0.1.7.dist-info/LICENSE
lamoom_cicd-0.1.7.dist-info/METADATA
lamoom_cicd-0.1.7.dist-info/WHEEL
lamoom_cicd-0.1.7.dist-info/RECORD
