Metadata-Version: 2.3
Name: lamoom-cicd
Version: 0.1.7
Summary: Library to test prompt quality
Author: Lamoom Engineering Team
Author-email: engineering@lamoom.com
Requires-Python: >=3.11,<4.0
Classifier: Programming Language :: Python :: 3
Classifier: Programming Language :: Python :: 3.11
Classifier: Programming Language :: Python :: 3.12
Classifier: Programming Language :: Python :: 3.13
Requires-Dist: lamoom (>=0.1.35,<0.2.0)
Requires-Dist: matplotlib (>=3.10.0,<4.0.0)
Requires-Dist: pandas (>=2.2.3,<3.0.0)
